{
  "light": {
    "backgroundColor": "#ededed",
    "backgroundTextStyle": "dark",
    "borderStyle": "black",
    "color": "#000000",
    "homeIconPath": "static/tabbar/home_dark.png",
    "homeSelectedIconPath": "static/tabbar/home_selected.png",
    "mineIconPath": "static/tabbar/mine_dark.png",
    "mineSelectedIconPath": "static/tabbar/mine_selected.png",
    "navigationBarBackgroundColor": "#ededed",
    "navigationBarTextStyle": "black",
    "selectedColor": "#4d80f0",
    "tabBackgroundColor": "#ededed"
  },
  "dark": {
    "backgroundColor": "#111111",
    "backgroundTextStyle": "light",
    "borderStyle": "black",
    "color": "#ffffff",
    "homeIconPath": "static/tabbar/home_light.png",
    "homeSelectedIconPath": "static/tabbar/home_selected.png",
    "mineIconPath": "static/tabbar/mine_light.png",
    "mineSelectedIconPath": "static/tabbar/mine_selected.png",
    "navigationBarBackgroundColor": "#111111",
    "navigationBarTextStyle": "white",
    "selectedColor": "#4d80f0",
    "tabBackgroundColor": "#111111"
  }
}
